pycarus/__init__.py
pycarus/calibration.py
pycarus/exceptions.py
pycarus/methods.py
pycarus/optimization.py
pycarus/preprocess.py
pycarus/utils.py
python_icarus-1.0.0.dist-info/WHEEL
python_icarus-1.0.0.dist-info/METADATA
python_icarus-1.0.0.dist-info/RECORD
