Metadata-Version: 2.3
Name: python-icarus
Version: 1.0.0
Summary: pycarus is a library to calibrate survey weights to match known population totals or proportions.
Keywords: survey,calibration,weights,statistics,sampling,raking,calage,calage sur marges,calmar,calmar2,icarus
Author: Nathan Etourneau
License: BSD 3-Clause License
Classifier: Development Status :: 4 - Beta
Classifier: Intended Audience :: Science/Research
Classifier: Topic :: Scientific/Engineering :: Mathematics
Classifier: Topic :: Scientific/Engineering :: Information Analysis
Classifier: License :: OSI Approved :: BSD License
Classifier: Programming Language :: Python :: 3
Classifier: Programming Language :: Python :: 3 :: Only
Classifier: Programming Language :: Python :: 3.10
Classifier: Programming Language :: Python :: 3.11
Classifier: Programming Language :: Python :: 3.12
Classifier: Programming Language :: Python :: 3.13
Requires-Dist: matplotlib>=3.10.0
Requires-Dist: numpy>=1.10.0
Requires-Dist: pandas>=1.0.0
Requires-Dist: scipy>=1.0.0
Requires-Dist: seaborn>=0.13.2
Requires-Python: >=3.10
